{"appleSKU":"","appleTeamID":"","enableCodelessAutoInitialization":true,"products":[{"id":"item01","type":0,"storeIDs":[],"defaultDescription":{"googleLocale":4,"title":"1 Box of 100 Polaroids","description":"You will need these to buy some cool stuff"},"screenshotPath":"","applePriceTier":0,"xiaomiPriceTier":0,"googlePrice":{"data":[59,0,0,131072],"num":0.59},"pricingTemplateID":"","descriptions":[],"payouts":[]},{"id":"item02","type":0,"storeIDs":[],"defaultDescription":{"googleLocale":4,"title":"5 Boxes of Polaroids","description":"You will need these to buy some cool stuff"},"screenshotPath":"","applePriceTier":0,"xiaomiPriceTier":0,"googlePrice":{"data":[119,0,0,131072],"num":1.19},"pricingTemplateID":"","descriptions":[],"payouts":[]},{"id":"item03","type":0,"storeIDs":[],"defaultDescription":{"googleLocale":4,"title":"Chest of 25 Boxes of Polaroids","description":"You will need these to buy some cool stuff"},"screenshotPath":"","applePriceTier":0,"xiaomiPriceTier":0,"googlePrice":{"data":[169,0,0,131072],"num":1.69},"pricingTemplateID":"","descriptions":[],"payouts":[]}]}